full-subtractor/fullSubtractor.v
module fullSubtractor (
    output difference, borrowOut, input a,b,borrowIn
);
    wire w0,w1,w2,w3,w4,w5,w6,w7,w8,w9;
    nor n0(w0,a);
    nor n1(w1,b);
    nor n2(w2,borrowIn);
    
    // ? borrowOut 
    and a0(w3,w0,borrowIn);
    and a1(w4,w0,b);
    and a2(w5,b,borrowIn);
    or o0(borrowOut,w3,w4,w5);
    
    // ? difference
    and a3(w6,w0,w1,borrowIn);
    and a4(w7,w0,b,w2);
    and a5(w8,a,w1,w2);
    and a6(w9,a,b,borrowIn);
    or o1(difference,w5,w6,w7,w8);
endmodule

full-subtractor/fullSubtractorTb.v
module test ();
    reg a,b,borrowIn;
    wire difference, borrowOut;
    fullSubtractor a1(difference,borrowOut,a,b,borrowIn);
    initial begin
        a=0;b=0;borrowIn=0;#1
        a=0;b=0;borrowIn=1;#1
        a=0;b=1;borrowIn=0;#1
        a=0;b=1;borrowIn=1;#1
        a=1;b=0;borrowIn=0;#1
        a=1;b=0;borrowIn=1;#1
        a=1;b=1;borrowIn=0;#1
        a=1;b=1;borrowIn=1;#1
        $finish;
    end
    initial begin
        $dumpfile("dump.vcd");
        $dumpvars(0,a1);
    end
endmodule

full-subtractor/dump.vcd
$date
	Fri May 05 21:11:13 2023
$end
$version
	Icarus Verilog
$end
$timescale
	1s
$end
$scope module test $end
$scope module a1 $end
$var wire 1 ! a $end
$var wire 1 " b $end
$var wire 1 # borrowIn $end
$var wire 1 $ borrowOut $end
$var wire 1 % difference $end
$var wire 1 & w0 $end
$var wire 1 ' w1 $end
$var wire 1 ( w2 $end
$var wire 1 ) w3 $end
$var wire 1 * w4 $end
$var wire 1 + w5 $end
$var wire 1 , w6 $end
$var wire 1 - w7 $end
$var wire 1 . w8 $end
$var wire 1 / w9 $end
$upscope $end
$upscope $end
$enddefinitions $end
$comment Show the parameter values. $end
$dumpall
$end
#0
$dumpvars
0/
0.
0-
0,
0+
0*
0)
1(
1'
1&
0%
0$
0#
0"
0!
$end
#1
1$
1%
0(
1)
1,
1#
#2
1-
1%
1(
0)
0,
0'
1*
0#
1"
#3
0-
0(
1)
1+
1#
#4
1.
0$
1%
1(
0)
1'
0*
0+
0&
0#
0"
1!
#5
0%
0.
0(
1#
#6
1(
0'
0#
1"
#7
1$
1%
0(
1+
1/
1#
