full-adder/fullAdder.v
module fullAdder (
    output sum,carryOut, input a,b,carryIn
);
    wire w0,w1,w2,w3;
    xor x0(w0,a,b);
    xor x1(sum,carryIn,w0);
    and a0(w1,a,b);
    and a1(w2,b,carryIn);
    and a2(w3,carryIn,a);
    or o0(carryOut,w1,w2,w3);
endmodule

full-adder/fullAdderTb.v
module test ();
    reg a,b,carryIn;
    wire sum,carryOut;
    fullAdder a1(sum,carryOut,a,b,carryIn);
    initial begin
        a=0;b=0;carryIn=0;#1
        a=0;b=0;carryIn=1;#1
        a=0;b=1;carryIn=0;#1
        a=0;b=1;carryIn=1;#1
        a=1;b=0;carryIn=0;#1
        a=1;b=0;carryIn=1;#1
        a=1;b=1;carryIn=0;#1
        a=1;b=1;carryIn=1;#1
        $finish;
    end
    initial begin
        $dumpfile("dump.vcd");
        $dumpvars(0,a1);
    end
endmodule

full-adder/dump.vcd
$date
	Fri May 05 20:39:49 2023
$end
$version
	Icarus Verilog
$end
$timescale
	1s
$end
$scope module test $end
$scope module a1 $end
$var wire 1 ! a $end
$var wire 1 " b $end
$var wire 1 # carryIn $end
$var wire 1 $ carryOut $end
$var wire 1 % sum $end
$var wire 1 & w0 $end
$var wire 1 ' w1 $end
$var wire 1 ( w2 $end
$var wire 1 ) w3 $end
$upscope $end
$upscope $end
$enddefinitions $end
$comment Show the parameter values. $end
$dumpall
$end
#0
$dumpvars
0)
0(
0'
0&
0%
0$
0#
0"
0!
$end
#1
1%
1#
#2
1&
0#
1"
#3
1$
0%
1(
1#
#4
0$
1%
0(
0#
0"
1!
#5
1$
0%
1)
1#
#6
0)
0&
1'
0#
1"
#7
1%
1(
1)
1#
