t-flipflop/tFlipFlop.v
module tFlipFlop (
    output reg q,input t,clock
);
    initial begin
        q <= 0;
    end
    always @(negedge clock) begin
        if(t)
            q <= ~q;
    end
endmodule

t-flipflop/tFlipFlopTb.v
module test (
    
);
    reg t,clock;
    wire q;
    tFlipFlop a1(q,t,clock);
    initial begin
        clock=1;
        forever #2 clock = ~clock;  
    end
    initial begin
        t = 1;
    end
    initial begin
        #200
        $finish;
    end
    initial begin
        $dumpfile("dump.vcd");
        $dumpvars(0,a1);
    end
endmodule

t-flipflop/dump.vcd
$date
	Wed May 10 15:42:35 2023
$end
$version
	Icarus Verilog
$end
$timescale
	1s
$end
$scope module test $end
$scope module a1 $end
$var wire 1 ! clock $end
$var wire 1 " t $end
$var reg 1 # q $end
$upscope $end
$upscope $end
$enddefinitions $end
$comment Show the parameter values. $end
$dumpall
$end
#0
$dumpvars
0#
1"
1!
$end
#2
1#
0!
#4
1!
#6
0#
0!
#8
1!
#10
1#
0!
#12
1!
#14
0#
0!
#16
1!
#18
1#
0!
#20
1!
#22
0#
0!
#24
1!
#26
1#
0!
#28
1!
#30
0#
0!
#32
1!
#34
1#
0!
#36
1!
#38
0#
0!
#40
1!
#42
1#
0!
#44
1!
#46
0#
0!
#48
1!
#50
1#
0!
#52
1!
#54
0#
0!
#56
1!
#58
1#
0!
#60
1!
#62
0#
0!
#64
1!
#66
1#
0!
#68
1!
#70
0#
0!
#72
1!
#74
1#
0!
#76
1!
#78
0#
0!
#80
1!
#82
1#
0!
#84
1!
#86
0#
0!
#88
1!
#90
1#
0!
#92
1!
#94
0#
0!
#96
1!
#98
1#
0!
#100
1!
#102
0#
0!
#104
1!
#106
1#
0!
#108
1!
#110
0#
0!
#112
1!
#114
1#
0!
#116
1!
#118
0#
0!
#120
1!
#122
1#
0!
#124
1!
#126
0#
0!
#128
1!
#130
1#
0!
#132
1!
#134
0#
0!
#136
1!
#138
1#
0!
#140
1!
#142
0#
0!
#144
1!
#146
1#
0!
#148
1!
#150
0#
0!
#152
1!
#154
1#
0!
#156
1!
#158
0#
0!
#160
1!
#162
1#
0!
#164
1!
#166
0#
0!
#168
1!
#170
1#
0!
#172
1!
#174
0#
0!
#176
1!
#178
1#
0!
#180
1!
#182
0#
0!
#184
1!
#186
1#
0!
#188
1!
#190
0#
0!
#192
1!
#194
1#
0!
#196
1!
#198
0#
0!
