twoXoneMux/twoXoneMux.v
module twoXoneMux (
    output out,input i1,i0,s0
);
    wire w0,w1,w2;
    nor n0(w0,s0);

    and a0(w1,w0,i0);
    and a1(w2,s0,i1);
    or o0(out,w1,w2);
endmodule

twoXoneMux/twoXoneMuxTb.v
module test (
    
);  
    reg i1,i0,s0;
    wire out;
    twoXoneMux a1(out,i1,i0,s0);
    initial begin
        i1=0;i0=0;s0=0;#1
        i1=0;i0=0;s0=1;#1
        i1=0;i0=1;s0=0;#1
        i1=0;i0=1;s0=1;#1
        i1=1;i0=0;s0=0;#1
        i1=1;i0=0;s0=1;#1
        i1=1;i0=1;s0=0;#1
        i1=1;i0=1;s0=1;#1
        $finish;
    end
    initial begin
        $dumpfile("dump.vcd");
        $dumpvars(0,a1);
    end
endmodule

twoXoneMux/dump.vcd
$date
	Sat May 06 19:40:44 2023
$end
$version
	Icarus Verilog
$end
$timescale
	1s
$end
$scope module test $end
$scope module a1 $end
$var wire 1 ! i0 $end
$var wire 1 " i1 $end
$var wire 1 # out $end
$var wire 1 $ s0 $end
$var wire 1 % w0 $end
$var wire 1 & w1 $end
$var wire 1 ' w2 $end
$upscope $end
$upscope $end
$enddefinitions $end
$comment Show the parameter values. $end
$dumpall
$end
#0
$dumpvars
0'
0&
1%
0$
0#
0"
0!
$end
#1
0%
1$
#2
1#
1&
1%
0$
1!
#3
0#
0&
0%
1$
#4
1%
0$
0!
1"
#5
1#
0%
1'
1$
#6
1&
1#
1%
0'
0$
1!
#7
0&
0%
1'
1$
