t-flipflop/tFlipFlop.v
module tFlipFlop (
    output reg q,input t,clock
);
    initial begin
        q <= 0;
    end
    always @(negedge clock) begin
        if(t)
            q <= ~q;
    end
endmodule

async-up-counter/design.sv
`include "../t-flipflop/tFlipFlop.v"


module async4BitUpCounter (
    output reg [3:0] out,input clock
);
    wire w0,w1,w2,w3;
    reg w4;
    initial begin
        w4 = 1;
        out[0] = 0;
    end
    tFlipFlop a0(w0,w4,clock);
    tFlipFlop a1(w1,w4,w0);
    tFlipFlop a2(w2,w4,w1);
    tFlipFlop a3(w3,w4,w2);
    always @(*) begin
        out[0] = w0;
        out[1] = w1;
        out[2] = w2;
        out[3] = w3;
    end
endmodule

async-up-counter/testBench.sv
`timescale 1ns/1ns
module test (
    
);
    reg clock;
    wire  reg [3:0] out;
    async4BitUpCounter a1(out,clock);
    initial begin
        clock=1;
        forever #2 clock = ~clock;  
    end
    initial begin
        #2000
        $finish;
    end
    initial begin
        $dumpfile("dump.vcd");
        $dumpvars(0,a1);
    end
endmodule

async-up-counter/dump.vcd
$date
	Thu Aug 03 13:25:33 2023
$end
$version
	Icarus Verilog
$end
$timescale
	1ns
$end
$scope module test $end
$scope module a1 $end
$var wire 1 ! clock $end
$var wire 1 " w3 $end
$var wire 1 # w2 $end
$var wire 1 $ w1 $end
$var wire 1 % w0 $end
$var reg 4 & out [3:0] $end
$var reg 1 ' w4 $end
$scope module a0 $end
$var wire 1 ! clock $end
$var wire 1 ' t $end
$var reg 1 % q $end
$upscope $end
$scope module a1 $end
$var wire 1 % clock $end
$var wire 1 ' t $end
$var reg 1 $ q $end
$upscope $end
$scope module a2 $end
$var wire 1 $ clock $end
$var wire 1 ' t $end
$var reg 1 # q $end
$upscope $end
$scope module a3 $end
$var wire 1 # clock $end
$var wire 1 ' t $end
$var reg 1 " q $end
$upscope $end
$upscope $end
$upscope $end
$enddefinitions $end
$comment Show the parameter values. $end
$dumpall
$end
#0
$dumpvars
1'
b1110 &
0%
1$
1#
1"
1!
$end
#2
b1111 &
1%
0!
#4
1!
#6
0"
0#
0$
b0 &
0%
0!
#8
1!
#10
b1 &
1%
0!
#12
1!
#14
1$
b10 &
0%
0!
#16
1!
#18
b11 &
1%
0!
#20
1!
#22
1#
0$
b100 &
0%
0!
#24
1!
#26
b101 &
1%
0!
#28
1!
#30
1$
b110 &
0%
0!
#32
1!
#34
b111 &
1%
0!
#36
1!
#38
1"
0#
0$
b1000 &
0%
0!
#40
1!
#42
b1001 &
1%
0!
#44
1!
#46
1$
b1010 &
0%
0!
#48
1!
#50
b1011 &
1%
0!
#52
1!
#54
1#
0$
b1100 &
0%
0!
#56
1!
#58
b1101 &
1%
0!
#60
1!
#62
1$
b1110 &
0%
0!
#64
1!
#66
b1111 &
1%
0!
#68
1!
#70
0"
0#
0$
b0 &
0%
0!
#72
1!
#74
b1 &
1%
0!
#76
1!
#78
1$
b10 &
0%
0!
#80
1!
#82
b11 &
1%
0!
#84
1!
#86
1#
0$
b100 &
0%
0!
#88
1!
#90
b101 &
1%
0!
#92
1!
#94
1$
b110 &
0%
0!
#96
1!
#98
b111 &
1%
0!
#100
1!
#102
1"
0#
0$
b1000 &
0%
0!
#104
1!
#106
b1001 &
1%
0!
#108
1!
#110
1$
b1010 &
0%
0!
#112
1!
#114
b1011 &
1%
0!
#116
1!
#118
1#
0$
b1100 &
0%
0!
#120
1!
#122
b1101 &
1%
0!
#124
1!
#126
1$
b1110 &
0%
0!
#128
1!
#130
b1111 &
1%
0!
#132
1!
#134
0"
0#
0$
b0 &
0%
0!
#136
1!
#138
b1 &
1%
0!
#140
1!
#142
1$
b10 &
0%
0!
#144
1!
#146
b11 &
1%
0!
#148
1!
#150
1#
0$
b100 &
0%
0!
#152
1!
#154
b101 &
1%
0!
#156
1!
#158
1$
b110 &
0%
0!
#160
1!
#162
b111 &
1%
0!
#164
1!
#166
1"
0#
0$
b1000 &
0%
0!
#168
1!
#170
b1001 &
1%
0!
#172
1!
#174
1$
b1010 &
0%
0!
#176
1!
#178
b1011 &
1%
0!
#180
1!
#182
1#
0$
b1100 &
0%
0!
#184
1!
#186
b1101 &
1%
0!
#188
1!
#190
1$
b1110 &
0%
0!
#192
1!
#194
b1111 &
1%
0!
#196
1!
#198
0"
0#
0$
b0 &
0%
0!
#200
1!
#202
b1 &
1%
0!
#204
1!
#206
1$
b10 &
0%
0!
#208
1!
#210
b11 &
1%
0!
#212
1!
#214
1#
0$
b100 &
0%
0!
#216
1!
#218
b101 &
1%
0!
#220
1!
#222
1$
b110 &
0%
0!
#224
1!
#226
b111 &
1%
0!
#228
1!
#230
1"
0#
0$
b1000 &
0%
0!
#232
1!
#234
b1001 &
1%
0!
#236
1!
#238
1$
b1010 &
0%
0!
#240
1!
#242
b1011 &
1%
0!
#244
1!
#246
1#
0$
b1100 &
0%
0!
#248
1!
#250
b1101 &
1%
0!
#252
1!
#254
1$
b1110 &
0%
0!
#256
1!
#258
b1111 &
1%
0!
#260
1!
#262
0"
0#
0$
b0 &
0%
0!
#264
1!
#266
b1 &
1%
0!
#268
1!
#270
1$
b10 &
0%
0!
#272
1!
#274
b11 &
1%
0!
#276
1!
#278
1#
0$
b100 &
0%
0!
#280
1!
#282
b101 &
1%
0!
#284
1!
#286
1$
b110 &
0%
0!
#288
1!
#290
b111 &
1%
0!
#292
1!
#294
1"
0#
0$
b1000 &
0%
0!
#296
1!
#298
b1001 &
1%
0!
#300
1!
#302
1$
b1010 &
0%
0!
#304
1!
#306
b1011 &
1%
0!
#308
1!
#310
1#
0$
b1100 &
0%
0!
#312
1!
#314
b1101 &
1%
0!
#316
1!
#318
1$
b1110 &
0%
0!
#320
1!
#322
b1111 &
1%
0!
#324
1!
#326
0"
0#
0$
b0 &
0%
0!
#328
1!
#330
b1 &
1%
0!
#332
1!
#334
1$
b10 &
0%
0!
#336
1!
#338
b11 &
1%
0!
#340
1!
#342
1#
0$
b100 &
0%
0!
#344
1!
#346
b101 &
1%
0!
#348
1!
#350
1$
b110 &
0%
0!
#352
1!
#354
b111 &
1%
0!
#356
1!
#358
1"
0#
0$
b1000 &
0%
0!
#360
1!
#362
b1001 &
1%
0!
#364
1!
#366
1$
b1010 &
0%
0!
#368
1!
#370
b1011 &
1%
0!
#372
1!
#374
1#
0$
b1100 &
0%
0!
#376
1!
#378
b1101 &
1%
0!
#380
1!
#382
1$
b1110 &
0%
0!
#384
1!
#386
b1111 &
1%
0!
#388
1!
#390
0"
0#
0$
b0 &
0%
0!
#392
1!
#394
b1 &
1%
0!
#396
1!
#398
1$
b10 &
0%
0!
#400
1!
#402
b11 &
1%
0!
#404
1!
#406
1#
0$
b100 &
0%
0!
#408
1!
#410
b101 &
1%
0!
#412
1!
#414
1$
b110 &
0%
0!
#416
1!
#418
b111 &
1%
0!
#420
1!
#422
1"
0#
0$
b1000 &
0%
0!
#424
1!
#426
b1001 &
1%
0!
#428
1!
#430
1$
b1010 &
0%
0!
#432
1!
#434
b1011 &
1%
0!
#436
1!
#438
1#
0$
b1100 &
0%
0!
#440
1!
#442
b1101 &
1%
0!
#444
1!
#446
1$
b1110 &
0%
0!
#448
1!
#450
b1111 &
1%
0!
#452
1!
#454
0"
0#
0$
b0 &
0%
0!
#456
1!
#458
b1 &
1%
0!
#460
1!
#462
1$
b10 &
0%
0!
#464
1!
#466
b11 &
1%
0!
#468
1!
#470
1#
0$
b100 &
0%
0!
#472
1!
#474
b101 &
1%
0!
#476
1!
#478
1$
b110 &
0%
0!
#480
1!
#482
b111 &
1%
0!
#484
1!
#486
1"
0#
0$
b1000 &
0%
0!
#488
1!
#490
b1001 &
1%
0!
#492
1!
#494
1$
b1010 &
0%
0!
#496
1!
#498
b1011 &
1%
0!
#500
1!
#502
1#
0$
b1100 &
0%
0!
#504
1!
#506
b1101 &
1%
0!
#508
1!
#510
1$
b1110 &
0%
0!
#512
1!
#514
b1111 &
1%
0!
#516
1!
#518
0"
0#
0$
b0 &
0%
0!
#520
1!
#522
b1 &
1%
0!
#524
1!
#526
1$
b10 &
0%
0!
#528
1!
#530
b11 &
1%
0!
#532
1!
#534
1#
0$
b100 &
0%
0!
#536
1!
#538
b101 &
1%
0!
#540
1!
#542
1$
b110 &
0%
0!
#544
1!
#546
b111 &
1%
0!
#548
1!
#550
1"
0#
0$
b1000 &
0%
0!
#552
1!
#554
b1001 &
1%
0!
#556
1!
#558
1$
b1010 &
0%
0!
#560
1!
#562
b1011 &
1%
0!
#564
1!
#566
1#
0$
b1100 &
0%
0!
#568
1!
#570
b1101 &
1%
0!
#572
1!
#574
1$
b1110 &
0%
0!
#576
1!
#578
b1111 &
1%
0!
#580
1!
#582
0"
0#
0$
b0 &
0%
0!
#584
1!
#586
b1 &
1%
0!
#588
1!
#590
1$
b10 &
0%
0!
#592
1!
#594
b11 &
1%
0!
#596
1!
#598
1#
0$
b100 &
0%
0!
#600
1!
#602
b101 &
1%
0!
#604
1!
#606
1$
b110 &
0%
0!
#608
1!
#610
b111 &
1%
0!
#612
1!
#614
1"
0#
0$
b1000 &
0%
0!
#616
1!
#618
b1001 &
1%
0!
#620
1!
#622
1$
b1010 &
0%
0!
#624
1!
#626
b1011 &
1%
0!
#628
1!
#630
1#
0$
b1100 &
0%
0!
#632
1!
#634
b1101 &
1%
0!
#636
1!
#638
1$
b1110 &
0%
0!
#640
1!
#642
b1111 &
1%
0!
#644
1!
#646
0"
0#
0$
b0 &
0%
0!
#648
1!
#650
b1 &
1%
0!
#652
1!
#654
1$
b10 &
0%
0!
#656
1!
#658
b11 &
1%
0!
#660
1!
#662
1#
0$
b100 &
0%
0!
#664
1!
#666
b101 &
1%
0!
#668
1!
#670
1$
b110 &
0%
0!
#672
1!
#674
b111 &
1%
0!
#676
1!
#678
1"
0#
0$
b1000 &
0%
0!
#680
1!
#682
b1001 &
1%
0!
#684
1!
#686
1$
b1010 &
0%
0!
#688
1!
#690
b1011 &
1%
0!
#692
1!
#694
1#
0$
b1100 &
0%
0!
#696
1!
#698
b1101 &
1%
0!
#700
1!
#702
1$
b1110 &
0%
0!
#704
1!
#706
b1111 &
1%
0!
#708
1!
#710
0"
0#
0$
b0 &
0%
0!
#712
1!
#714
b1 &
1%
0!
#716
1!
#718
1$
b10 &
0%
0!
#720
1!
#722
b11 &
1%
0!
#724
1!
#726
1#
0$
b100 &
0%
0!
#728
1!
#730
b101 &
1%
0!
#732
1!
#734
1$
b110 &
0%
0!
#736
1!
#738
b111 &
1%
0!
#740
1!
#742
1"
0#
0$
b1000 &
0%
0!
#744
1!
#746
b1001 &
1%
0!
#748
1!
#750
1$
b1010 &
0%
0!
#752
1!
#754
b1011 &
1%
0!
#756
1!
#758
1#
0$
b1100 &
0%
0!
#760
1!
#762
b1101 &
1%
0!
#764
1!
#766
1$
b1110 &
0%
0!
#768
1!
#770
b1111 &
1%
0!
#772
1!
#774
0"
0#
0$
b0 &
0%
0!
#776
1!
#778
b1 &
1%
0!
#780
1!
#782
1$
b10 &
0%
0!
#784
1!
#786
b11 &
1%
0!
#788
1!
#790
1#
0$
b100 &
0%
0!
#792
1!
#794
b101 &
1%
0!
#796
1!
#798
1$
b110 &
0%
0!
#800
1!
#802
b111 &
1%
0!
#804
1!
#806
1"
0#
0$
b1000 &
0%
0!
#808
1!
#810
b1001 &
1%
0!
#812
1!
#814
1$
b1010 &
0%
0!
#816
1!
#818
b1011 &
1%
0!
#820
1!
#822
1#
0$
b1100 &
0%
0!
#824
1!
#826
b1101 &
1%
0!
#828
1!
#830
1$
b1110 &
0%
0!
#832
1!
#834
b1111 &
1%
0!
#836
1!
#838
0"
0#
0$
b0 &
0%
0!
#840
1!
#842
b1 &
1%
0!
#844
1!
#846
1$
b10 &
0%
0!
#848
1!
#850
b11 &
1%
0!
#852
1!
#854
1#
0$
b100 &
0%
0!
#856
1!
#858
b101 &
1%
0!
#860
1!
#862
1$
b110 &
0%
0!
#864
1!
#866
b111 &
1%
0!
#868
1!
#870
1"
0#
0$
b1000 &
0%
0!
#872
1!
#874
b1001 &
1%
0!
#876
1!
#878
1$
b1010 &
0%
0!
#880
1!
#882
b1011 &
1%
0!
#884
1!
#886
1#
0$
b1100 &
0%
0!
#888
1!
#890
b1101 &
1%
0!
#892
1!
#894
1$
b1110 &
0%
0!
#896
1!
#898
b1111 &
1%
0!
#900
1!
#902
0"
0#
0$
b0 &
0%
0!
#904
1!
#906
b1 &
1%
0!
#908
1!
#910
1$
b10 &
0%
0!
#912
1!
#914
b11 &
1%
0!
#916
1!
#918
1#
0$
b100 &
0%
0!
#920
1!
#922
b101 &
1%
0!
#924
1!
#926
1$
b110 &
0%
0!
#928
1!
#930
b111 &
1%
0!
#932
1!
#934
1"
0#
0$
b1000 &
0%
0!
#936
1!
#938
b1001 &
1%
0!
#940
1!
#942
1$
b1010 &
0%
0!
#944
1!
#946
b1011 &
1%
0!
#948
1!
#950
1#
0$
b1100 &
0%
0!
#952
1!
#954
b1101 &
1%
0!
#956
1!
#958
1$
b1110 &
0%
0!
#960
1!
#962
b1111 &
1%
0!
#964
1!
#966
0"
0#
0$
b0 &
0%
0!
#968
1!
#970
b1 &
1%
0!
#972
1!
#974
1$
b10 &
0%
0!
#976
1!
#978
b11 &
1%
0!
#980
1!
#982
1#
0$
b100 &
0%
0!
#984
1!
#986
b101 &
1%
0!
#988
1!
#990
1$
b110 &
0%
0!
#992
1!
#994
b111 &
1%
0!
#996
1!
#998
1"
0#
0$
b1000 &
0%
0!
#1000
1!
#1002
b1001 &
1%
0!
#1004
1!
#1006
1$
b1010 &
0%
0!
#1008
1!
#1010
b1011 &
1%
0!
#1012
1!
#1014
1#
0$
b1100 &
0%
0!
#1016
1!
#1018
b1101 &
1%
0!
#1020
1!
#1022
1$
b1110 &
0%
0!
#1024
1!
#1026
b1111 &
1%
0!
#1028
1!
#1030
0"
0#
0$
b0 &
0%
0!
#1032
1!
#1034
b1 &
1%
0!
#1036
1!
#1038
1$
b10 &
0%
0!
#1040
1!
#1042
b11 &
1%
0!
#1044
1!
#1046
1#
0$
b100 &
0%
0!
#1048
1!
#1050
b101 &
1%
0!
#1052
1!
#1054
1$
b110 &
0%
0!
#1056
1!
#1058
b111 &
1%
0!
#1060
1!
#1062
1"
0#
0$
b1000 &
0%
0!
#1064
1!
#1066
b1001 &
1%
0!
#1068
1!
#1070
1$
b1010 &
0%
0!
#1072
1!
#1074
b1011 &
1%
0!
#1076
1!
#1078
1#
0$
b1100 &
0%
0!
#1080
1!
#1082
b1101 &
1%
0!
#1084
1!
#1086
1$
b1110 &
0%
0!
#1088
1!
#1090
b1111 &
1%
0!
#1092
1!
#1094
0"
0#
0$
b0 &
0%
0!
#1096
1!
#1098
b1 &
1%
0!
#1100
1!
#1102
1$
b10 &
0%
0!
#1104
1!
#1106
b11 &
1%
0!
#1108
1!
#1110
1#
0$
b100 &
0%
0!
#1112
1!
#1114
b101 &
1%
0!
#1116
1!
#1118
1$
b110 &
0%
0!
#1120
1!
#1122
b111 &
1%
0!
#1124
1!
#1126
1"
0#
0$
b1000 &
0%
0!
#1128
1!
#1130
b1001 &
1%
0!
#1132
1!
#1134
1$
b1010 &
0%
0!
#1136
1!
#1138
b1011 &
1%
0!
#1140
1!
#1142
1#
0$
b1100 &
0%
0!
#1144
1!
#1146
b1101 &
1%
0!
#1148
1!
#1150
1$
b1110 &
0%
0!
#1152
1!
#1154
b1111 &
1%
0!
#1156
1!
#1158
0"
0#
0$
b0 &
0%
0!
#1160
1!
#1162
b1 &
1%
0!
#1164
1!
#1166
1$
b10 &
0%
0!
#1168
1!
#1170
b11 &
1%
0!
#1172
1!
#1174
1#
0$
b100 &
0%
0!
#1176
1!
#1178
b101 &
1%
0!
#1180
1!
#1182
1$
b110 &
0%
0!
#1184
1!
#1186
b111 &
1%
0!
#1188
1!
#1190
1"
0#
0$
b1000 &
0%
0!
#1192
1!
#1194
b1001 &
1%
0!
#1196
1!
#1198
1$
b1010 &
0%
0!
#1200
1!
#1202
b1011 &
1%
0!
#1204
1!
#1206
1#
0$
b1100 &
0%
0!
#1208
1!
#1210
b1101 &
1%
0!
#1212
1!
#1214
1$
b1110 &
0%
0!
#1216
1!
#1218
b1111 &
1%
0!
#1220
1!
#1222
0"
0#
0$
b0 &
0%
0!
#1224
1!
#1226
b1 &
1%
0!
#1228
1!
#1230
1$
b10 &
0%
0!
#1232
1!
#1234
b11 &
1%
0!
#1236
1!
#1238
1#
0$
b100 &
0%
0!
#1240
1!
#1242
b101 &
1%
0!
#1244
1!
#1246
1$
b110 &
0%
0!
#1248
1!
#1250
b111 &
1%
0!
#1252
1!
#1254
1"
0#
0$
b1000 &
0%
0!
#1256
1!
#1258
b1001 &
1%
0!
#1260
1!
#1262
1$
b1010 &
0%
0!
#1264
1!
#1266
b1011 &
1%
0!
#1268
1!
#1270
1#
0$
b1100 &
0%
0!
#1272
1!
#1274
b1101 &
1%
0!
#1276
1!
#1278
1$
b1110 &
0%
0!
#1280
1!
#1282
b1111 &
1%
0!
#1284
1!
#1286
0"
0#
0$
b0 &
0%
0!
#1288
1!
#1290
b1 &
1%
0!
#1292
1!
#1294
1$
b10 &
0%
0!
#1296
1!
#1298
b11 &
1%
0!
#1300
1!
#1302
1#
0$
b100 &
0%
0!
#1304
1!
#1306
b101 &
1%
0!
#1308
1!
#1310
1$
b110 &
0%
0!
#1312
1!
#1314
b111 &
1%
0!
#1316
1!
#1318
1"
0#
0$
b1000 &
0%
0!
#1320
1!
#1322
b1001 &
1%
0!
#1324
1!
#1326
1$
b1010 &
0%
0!
#1328
1!
#1330
b1011 &
1%
0!
#1332
1!
#1334
1#
0$
b1100 &
0%
0!
#1336
1!
#1338
b1101 &
1%
0!
#1340
1!
#1342
1$
b1110 &
0%
0!
#1344
1!
#1346
b1111 &
1%
0!
#1348
1!
#1350
0"
0#
0$
b0 &
0%
0!
#1352
1!
#1354
b1 &
1%
0!
#1356
1!
#1358
1$
b10 &
0%
0!
#1360
1!
#1362
b11 &
1%
0!
#1364
1!
#1366
1#
0$
b100 &
0%
0!
#1368
1!
#1370
b101 &
1%
0!
#1372
1!
#1374
1$
b110 &
0%
0!
#1376
1!
#1378
b111 &
1%
0!
#1380
1!
#1382
1"
0#
0$
b1000 &
0%
0!
#1384
1!
#1386
b1001 &
1%
0!
#1388
1!
#1390
1$
b1010 &
0%
0!
#1392
1!
#1394
b1011 &
1%
0!
#1396
1!
#1398
1#
0$
b1100 &
0%
0!
#1400
1!
#1402
b1101 &
1%
0!
#1404
1!
#1406
1$
b1110 &
0%
0!
#1408
1!
#1410
b1111 &
1%
0!
#1412
1!
#1414
0"
0#
0$
b0 &
0%
0!
#1416
1!
#1418
b1 &
1%
0!
#1420
1!
#1422
1$
b10 &
0%
0!
#1424
1!
#1426
b11 &
1%
0!
#1428
1!
#1430
1#
0$
b100 &
0%
0!
#1432
1!
#1434
b101 &
1%
0!
#1436
1!
#1438
1$
b110 &
0%
0!
#1440
1!
#1442
b111 &
1%
0!
#1444
1!
#1446
1"
0#
0$
b1000 &
0%
0!
#1448
1!
#1450
b1001 &
1%
0!
#1452
1!
#1454
1$
b1010 &
0%
0!
#1456
1!
#1458
b1011 &
1%
0!
#1460
1!
#1462
1#
0$
b1100 &
0%
0!
#1464
1!
#1466
b1101 &
1%
0!
#1468
1!
#1470
1$
b1110 &
0%
0!
#1472
1!
#1474
b1111 &
1%
0!
#1476
1!
#1478
0"
0#
0$
b0 &
0%
0!
#1480
1!
#1482
b1 &
1%
0!
#1484
1!
#1486
1$
b10 &
0%
0!
#1488
1!
#1490
b11 &
1%
0!
#1492
1!
#1494
1#
0$
b100 &
0%
0!
#1496
1!
#1498
b101 &
1%
0!
#1500
1!
#1502
1$
b110 &
0%
0!
#1504
1!
#1506
b111 &
1%
0!
#1508
1!
#1510
1"
0#
0$
b1000 &
0%
0!
#1512
1!
#1514
b1001 &
1%
0!
#1516
1!
#1518
1$
b1010 &
0%
0!
#1520
1!
#1522
b1011 &
1%
0!
#1524
1!
#1526
1#
0$
b1100 &
0%
0!
#1528
1!
#1530
b1101 &
1%
0!
#1532
1!
#1534
1$
b1110 &
0%
0!
#1536
1!
#1538
b1111 &
1%
0!
#1540
1!
#1542
0"
0#
0$
b0 &
0%
0!
#1544
1!
#1546
b1 &
1%
0!
#1548
1!
#1550
1$
b10 &
0%
0!
#1552
1!
#1554
b11 &
1%
0!
#1556
1!
#1558
1#
0$
b100 &
0%
0!
#1560
1!
#1562
b101 &
1%
0!
#1564
1!
#1566
1$
b110 &
0%
0!
#1568
1!
#1570
b111 &
1%
0!
#1572
1!
#1574
1"
0#
0$
b1000 &
0%
0!
#1576
1!
#1578
b1001 &
1%
0!
#1580
1!
#1582
1$
b1010 &
0%
0!
#1584
1!
#1586
b1011 &
1%
0!
#1588
1!
#1590
1#
0$
b1100 &
0%
0!
#1592
1!
#1594
b1101 &
1%
0!
#1596
1!
#1598
1$
b1110 &
0%
0!
#1600
1!
#1602
b1111 &
1%
0!
#1604
1!
#1606
0"
0#
0$
b0 &
0%
0!
#1608
1!
#1610
b1 &
1%
0!
#1612
1!
#1614
1$
b10 &
0%
0!
#1616
1!
#1618
b11 &
1%
0!
#1620
1!
#1622
1#
0$
b100 &
0%
0!
#1624
1!
#1626
b101 &
1%
0!
#1628
1!
#1630
1$
b110 &
0%
0!
#1632
1!
#1634
b111 &
1%
0!
#1636
1!
#1638
1"
0#
0$
b1000 &
0%
0!
#1640
1!
#1642
b1001 &
1%
0!
#1644
1!
#1646
1$
b1010 &
0%
0!
#1648
1!
#1650
b1011 &
1%
0!
#1652
1!
#1654
1#
0$
b1100 &
0%
0!
#1656
1!
#1658
b1101 &
1%
0!
#1660
1!
#1662
1$
b1110 &
0%
0!
#1664
1!
#1666
b1111 &
1%
0!
#1668
1!
#1670
0"
0#
0$
b0 &
0%
0!
#1672
1!
#1674
b1 &
1%
0!
#1676
1!
#1678
1$
b10 &
0%
0!
#1680
1!
#1682
b11 &
1%
0!
#1684
1!
#1686
1#
0$
b100 &
0%
0!
#1688
1!
#1690
b101 &
1%
0!
#1692
1!
#1694
1$
b110 &
0%
0!
#1696
1!
#1698
b111 &
1%
0!
#1700
1!
#1702
1"
0#
0$
b1000 &
0%
0!
#1704
1!
#1706
b1001 &
1%
0!
#1708
1!
#1710
1$
b1010 &
0%
0!
#1712
1!
#1714
b1011 &
1%
0!
#1716
1!
#1718
1#
0$
b1100 &
0%
0!
#1720
1!
#1722
b1101 &
1%
0!
#1724
1!
#1726
1$
b1110 &
0%
0!
#1728
1!
#1730
b1111 &
1%
0!
#1732
1!
#1734
0"
0#
0$
b0 &
0%
0!
#1736
1!
#1738
b1 &
1%
0!
#1740
1!
#1742
1$
b10 &
0%
0!
#1744
1!
#1746
b11 &
1%
0!
#1748
1!
#1750
1#
0$
b100 &
0%
0!
#1752
1!
#1754
b101 &
1%
0!
#1756
1!
#1758
1$
b110 &
0%
0!
#1760
1!
#1762
b111 &
1%
0!
#1764
1!
#1766
1"
0#
0$
b1000 &
0%
0!
#1768
1!
#1770
b1001 &
1%
0!
#1772
1!
#1774
1$
b1010 &
0%
0!
#1776
1!
#1778
b1011 &
1%
0!
#1780
1!
#1782
1#
0$
b1100 &
0%
0!
#1784
1!
#1786
b1101 &
1%
0!
#1788
1!
#1790
1$
b1110 &
0%
0!
#1792
1!
#1794
b1111 &
1%
0!
#1796
1!
#1798
0"
0#
0$
b0 &
0%
0!
#1800
1!
#1802
b1 &
1%
0!
#1804
1!
#1806
1$
b10 &
0%
0!
#1808
1!
#1810
b11 &
1%
0!
#1812
1!
#1814
1#
0$
b100 &
0%
0!
#1816
1!
#1818
b101 &
1%
0!
#1820
1!
#1822
1$
b110 &
0%
0!
#1824
1!
#1826
b111 &
1%
0!
#1828
1!
#1830
1"
0#
0$
b1000 &
0%
0!
#1832
1!
#1834
b1001 &
1%
0!
#1836
1!
#1838
1$
b1010 &
0%
0!
#1840
1!
#1842
b1011 &
1%
0!
#1844
1!
#1846
1#
0$
b1100 &
0%
0!
#1848
1!
#1850
b1101 &
1%
0!
#1852
1!
#1854
1$
b1110 &
0%
0!
#1856
1!
#1858
b1111 &
1%
0!
#1860
1!
#1862
0"
0#
0$
b0 &
0%
0!
#1864
1!
#1866
b1 &
1%
0!
#1868
1!
#1870
1$
b10 &
0%
0!
#1872
1!
#1874
b11 &
1%
0!
#1876
1!
#1878
1#
0$
b100 &
0%
0!
#1880
1!
#1882
b101 &
1%
0!
#1884
1!
#1886
1$
b110 &
0%
0!
#1888
1!
#1890
b111 &
1%
0!
#1892
1!
#1894
1"
0#
0$
b1000 &
0%
0!
#1896
1!
#1898
b1001 &
1%
0!
#1900
1!
#1902
1$
b1010 &
0%
0!
#1904
1!
#1906
b1011 &
1%
0!
#1908
1!
#1910
1#
0$
b1100 &
0%
0!
#1912
1!
#1914
b1101 &
1%
0!
#1916
1!
#1918
1$
b1110 &
0%
0!
#1920
1!
#1922
b1111 &
1%
0!
#1924
1!
#1926
0"
0#
0$
b0 &
0%
0!
#1928
1!
#1930
b1 &
1%
0!
#1932
1!
#1934
1$
b10 &
0%
0!
#1936
1!
#1938
b11 &
1%
0!
#1940
1!
#1942
1#
0$
b100 &
0%
0!
#1944
1!
#1946
b101 &
1%
0!
#1948
1!
#1950
1$
b110 &
0%
0!
#1952
1!
#1954
b111 &
1%
0!
#1956
1!
#1958
1"
0#
0$
b1000 &
0%
0!
#1960
1!
#1962
b1001 &
1%
0!
#1964
1!
#1966
1$
b1010 &
0%
0!
#1968
1!
#1970
b1011 &
1%
0!
#1972
1!
#1974
1#
0$
b1100 &
0%
0!
#1976
1!
#1978
b1101 &
1%
0!
#1980
1!
#1982
1$
b1110 &
0%
0!
#1984
1!
#1986
b1111 &
1%
0!
#1988
1!
#1990
0"
0#
0$
b0 &
0%
0!
#1992
1!
#1994
b1 &
1%
0!
#1996
1!
#1998
1$
b10 &
0%
0!
