twoXoneMux/twoXoneMux.v
module twoXoneMux (
    output out,input i1,i0,s0
);
    wire w0,w1,w2;
    nor n0(w0,s0);

    and a0(w1,w0,i0);
    and a1(w2,s0,i1);
    or o0(out,w1,w2);
endmodule

fourXoneMux/fourXoneMux.v
`include "../twoXoneMux/twoXoneMux.v"

module fourXoneMux (
    output out,input i3,i2,i1,i0,s1,s0
);
    wire w0,w1;
    twoXoneMux a0(w0,i1,i0,s0);
    twoXoneMux a1(w1,i3,i2,s0);
    twoXoneMux a2(out,w1,w0,s1);
endmodule

fourXoneMux/fourXoneMuxTb.v
`timescale 1ns/1ns
module test (
    
);
    reg i3,i2,i1,i0,s1,s0;
    wire out;
    fourXoneMux a1(out,i3,i2,i1,i0,s1,s0);
    initial begin
        i3=0;i2=0;i1=0;i0=0;s1=0;s0=0;#1
        i3=0;i2=0;i1=0;i0=0;s1=0;s0=1;#1
        i3=0;i2=0;i1=0;i0=0;s1=1;s0=0;#1
        i3=0;i2=0;i1=0;i0=0;s1=1;s0=1;#1
        i3=0;i2=0;i1=0;i0=1;s1=0;s0=0;#1
        i3=0;i2=0;i1=0;i0=1;s1=0;s0=1;#1
        i3=0;i2=0;i1=0;i0=1;s1=1;s0=0;#1
        i3=0;i2=0;i1=0;i0=1;s1=1;s0=1;#1
        i3=0;i2=0;i1=1;i0=0;s1=0;s0=0;#1
        i3=0;i2=0;i1=1;i0=0;s1=0;s0=1;#1
        i3=0;i2=0;i1=1;i0=0;s1=1;s0=0;#1
        i3=0;i2=0;i1=1;i0=0;s1=1;s0=1;#1
        i3=0;i2=0;i1=1;i0=1;s1=0;s0=0;#1
        i3=0;i2=0;i1=1;i0=1;s1=0;s0=1;#1
        i3=0;i2=0;i1=1;i0=1;s1=1;s0=0;#1
        i3=0;i2=0;i1=1;i0=1;s1=1;s0=1;#1
        i3=0;i2=1;i1=0;i0=0;s1=0;s0=0;#1
        i3=0;i2=1;i1=0;i0=0;s1=0;s0=1;#1
        i3=0;i2=1;i1=0;i0=0;s1=1;s0=0;#1
        i3=0;i2=1;i1=0;i0=0;s1=1;s0=1;#1
        i3=0;i2=1;i1=0;i0=1;s1=0;s0=0;#1
        i3=0;i2=1;i1=0;i0=1;s1=0;s0=1;#1
        i3=0;i2=1;i1=0;i0=1;s1=1;s0=0;#1
        i3=0;i2=1;i1=0;i0=1;s1=1;s0=1;#1
        i3=0;i2=1;i1=1;i0=0;s1=0;s0=0;#1
        i3=0;i2=1;i1=1;i0=0;s1=0;s0=1;#1
        i3=0;i2=1;i1=1;i0=0;s1=1;s0=0;#1
        i3=0;i2=1;i1=1;i0=0;s1=1;s0=1;#1
        i3=0;i2=1;i1=1;i0=1;s1=0;s0=0;#1
        i3=0;i2=1;i1=1;i0=1;s1=0;s0=1;#1
        i3=0;i2=1;i1=1;i0=1;s1=1;s0=0;#1
        i3=0;i2=1;i1=1;i0=1;s1=1;s0=1;#1
        i3=1;i2=0;i1=0;i0=0;s1=0;s0=0;#1
        i3=1;i2=0;i1=0;i0=0;s1=0;s0=1;#1
        i3=1;i2=0;i1=0;i0=0;s1=1;s0=0;#1
        i3=1;i2=0;i1=0;i0=0;s1=1;s0=1;#1
        i3=1;i2=0;i1=0;i0=1;s1=0;s0=0;#1
        i3=1;i2=0;i1=0;i0=1;s1=0;s0=1;#1
        i3=1;i2=0;i1=0;i0=1;s1=1;s0=0;#1
        i3=1;i2=0;i1=0;i0=1;s1=1;s0=1;#1
        i3=1;i2=0;i1=1;i0=0;s1=0;s0=0;#1
        i3=1;i2=0;i1=1;i0=0;s1=0;s0=1;#1
        i3=1;i2=0;i1=1;i0=0;s1=1;s0=0;#1
        i3=1;i2=0;i1=1;i0=0;s1=1;s0=1;#1
        i3=1;i2=0;i1=1;i0=1;s1=0;s0=0;#1
        i3=1;i2=0;i1=1;i0=1;s1=0;s0=1;#1
        i3=1;i2=0;i1=1;i0=1;s1=1;s0=0;#1
        i3=1;i2=0;i1=1;i0=1;s1=1;s0=1;#1
        i3=1;i2=1;i1=0;i0=0;s1=0;s0=0;#1
        i3=1;i2=1;i1=0;i0=0;s1=0;s0=1;#1
        i3=1;i2=1;i1=0;i0=0;s1=1;s0=0;#1
        i3=1;i2=1;i1=0;i0=0;s1=1;s0=1;#1
        i3=1;i2=1;i1=0;i0=1;s1=0;s0=0;#1
        i3=1;i2=1;i1=0;i0=1;s1=0;s0=1;#1
        i3=1;i2=1;i1=0;i0=1;s1=1;s0=0;#1
        i3=1;i2=1;i1=0;i0=1;s1=1;s0=1;#1
        i3=1;i2=1;i1=1;i0=0;s1=0;s0=0;#1
        i3=1;i2=1;i1=1;i0=0;s1=0;s0=1;#1
        i3=1;i2=1;i1=1;i0=0;s1=1;s0=0;#1
        i3=1;i2=1;i1=1;i0=0;s1=1;s0=1;#1
        i3=1;i2=1;i1=1;i0=1;s1=0;s0=0;#1
        i3=1;i2=1;i1=1;i0=1;s1=0;s0=1;#1
        i3=1;i2=1;i1=1;i0=1;s1=1;s0=0;#1
        i3=1;i2=1;i1=1;i0=1;s1=1;s0=1;#1
        $finish;
    end
    initial begin
        $dumpfile("dump.vcd");
        $dumpvars(0,a1);
    end
endmodule

fourXoneMux/dump.vcd
$date
	Sat May 06 19:55:19 2023
$end
$version
	Icarus Verilog
$end
$timescale
	1ns
$end
$scope module test $end
$scope module a1 $end
$var wire 1 ! i0 $end
$var wire 1 " i1 $end
$var wire 1 # i2 $end
$var wire 1 $ i3 $end
$var wire 1 % s0 $end
$var wire 1 & s1 $end
$var wire 1 ' w1 $end
$var wire 1 ( w0 $end
$var wire 1 ) out $end
$scope module a0 $end
$var wire 1 ! i0 $end
$var wire 1 " i1 $end
$var wire 1 ( out $end
$var wire 1 % s0 $end
$var wire 1 * w0 $end
$var wire 1 + w1 $end
$var wire 1 , w2 $end
$upscope $end
$scope module a1 $end
$var wire 1 # i0 $end
$var wire 1 $ i1 $end
$var wire 1 ' out $end
$var wire 1 % s0 $end
$var wire 1 - w0 $end
$var wire 1 . w1 $end
$var wire 1 / w2 $end
$upscope $end
$scope module a2 $end
$var wire 1 ( i0 $end
$var wire 1 ' i1 $end
$var wire 1 ) out $end
$var wire 1 & s0 $end
$var wire 1 0 w0 $end
$var wire 1 1 w1 $end
$var wire 1 2 w2 $end
$upscope $end
$upscope $end
$upscope $end
$enddefinitions $end
$comment Show the parameter values. $end
$dumpall
$end
#0
$dumpvars
02
01
10
0/
0.
1-
0,
0+
1*
0)
0(
0'
0&
0%
0$
0#
0"
0!
$end
#1
0*
0-
1%
#2
1*
1-
00
0%
1&
#3
0*
0-
1%
#4
1)
11
1(
1+
1*
1-
10
0%
0&
1!
#5
0)
01
0(
0+
0*
0-
1%
#6
1(
1+
1*
1-
00
0%
1&
#7
0(
0+
0*
0-
1%
#8
1*
1-
10
0%
0&
0!
1"
#9
1)
11
1(
0*
1,
0-
1%
#10
0)
0(
01
1*
0,
1-
00
0%
1&
#11
1(
0*
1,
0-
1%
#12
1)
1+
1(
11
1*
0,
1-
10
0%
0&
1!
#13
0+
0*
1,
0-
1%
#14
0)
1+
1(
01
1*
0,
1-
00
0%
1&
#15
0+
0*
1,
0-
1%
#16
1'
1.
0(
1*
1-
10
0,
0%
0&
0!
0"
1#
#17
0'
0.
0*
0-
1%
#18
1)
12
1'
1.
1*
1-
00
0%
1&
#19
0)
02
0'
0.
0*
0-
1%
#20
1)
11
1(
1'
1+
1.
1*
1-
10
0%
0&
1!
#21
0)
01
0(
0'
0+
0.
0*
0-
1%
#22
1)
12
1(
1'
1+
1.
1*
1-
00
0%
1&
#23
0)
02
0(
0'
0+
0.
0*
0-
1%
#24
1'
1.
1*
1-
10
0%
0&
0!
1"
#25
1)
11
0'
1(
0.
0*
1,
0-
1%
#26
12
1'
1)
0(
1.
01
1*
0,
1-
00
0%
1&
#27
0)
02
0'
1(
0.
0*
1,
0-
1%
#28
1'
1)
1+
1(
1.
11
1*
0,
1-
10
0%
0&
1!
#29
0'
0+
0.
0*
1,
0-
1%
#30
12
1'
1)
1+
1(
1.
01
1*
0,
1-
00
0%
1&
#31
0)
02
0'
0+
0.
0*
1,
0-
1%
#32
0(
1*
1-
10
0,
0%
0&
0!
0"
0#
1$
#33
1'
0*
0-
1/
1%
#34
0'
0)
1*
1-
0/
00
02
0%
1&
#35
1)
12
1'
0*
0-
1/
1%
#36
11
1(
1+
0'
1)
1*
1-
0/
10
02
0%
0&
1!
#37
0)
01
0(
0+
1'
0*
0-
1/
1%
#38
1(
1+
0'
0)
1*
1-
0/
00
02
0%
1&
#39
1)
0(
12
0+
1'
0*
0-
1/
1%
#40
0'
0)
1*
1-
0/
10
02
0%
0&
0!
1"
#41
1)
11
1(
1'
0*
1,
0-
1/
1%
#42
0)
0(
0'
01
1*
0,
1-
0/
00
02
0%
1&
#43
1)
12
1(
1'
0*
1,
0-
1/
1%
#44
1+
1(
0'
11
1)
1*
0,
1-
0/
10
02
0%
0&
1!
#45
0+
1'
0*
1,
0-
1/
1%
#46
0)
1+
1(
0'
01
1*
0,
1-
0/
00
02
0%
1&
#47
1)
12
0+
1'
0*
1,
0-
1/
1%
#48
1.
1'
0)
0(
1*
1-
0/
10
02
0,
0%
0&
0!
0"
1#
#49
0.
0*
0-
1/
1%
#50
1.
1'
1)
1*
1-
0/
00
12
0%
1&
#51
0.
0*
0-
1/
1%
#52
11
1(
1+
1.
1'
1)
1*
1-
0/
10
02
0%
0&
1!
#53
0)
01
0(
0+
0.
0*
0-
1/
1%
#54
1(
1+
1.
1'
1)
1*
1-
0/
00
12
0%
1&
#55
0(
0+
0.
0*
0-
1/
1%
#56
1.
1'
0)
1*
1-
0/
10
02
0%
0&
0!
1"
#57
1)
11
1(
0.
0*
1,
0-
1/
1%
#58
1)
0(
1.
1'
01
1*
0,
1-
0/
00
12
0%
1&
#59
1(
0.
0*
1,
0-
1/
1%
#60
1+
1(
1.
1'
11
1)
1*
0,
1-
0/
10
02
0%
0&
1!
#61
0+
0.
0*
1,
0-
1/
1%
#62
1)
1+
1(
1.
1'
01
1*
0,
1-
0/
00
12
0%
1&
#63
0+
0.
0*
1,
0-
1/
1%
